{
  "url": "https://www.myhome.ge/ka/pr/13739324/iyideba-Zveli-ashenebuli-bina-digmis-masivshi-a.-beliashvilis-qucha-3-oTaxiani",
  "price": 50000,
  "m2Price": 649.3506493506494,
  "title": "იყიდება ძველი აშენებული ბინა დიღმის მასივში",
  "stats": {
    "_id": "6397a45537bca9f5cc041252",
    "name": "ახალიგარემონტებულიდიღმისმასივშიOLD",
    "__v": 0,
    "averageM2Price": 938.0387391573024,
    "averagePrice": 71767.85714285714,
    "propertiesTotal": 28,
    "region": "დიღმის მასივში",
    "status": "ახალი გარემონტებული"
  }
}